picellcounter/PCA.py
picellcounter/__init__.py
picellcounter/bd_resample.py
picellcounter/bdreg.py
picellcounter/cellcounter.py
picellcounter/clusterSM.py
picellcounter/collect_selected_bstack.py
picellcounter/getboundary.py
picellcounter/list_set.py
picellcounter/main.py
picellcounter/pca_bdreg.py
picellcounter/recordIDX.py
picellcounter/reg_bd3.py
picellcounter/reg_bd_svd.py
picellcounter/serverside.py
picellcounter/sum_binary.py
picellcounter-1.0.4.data/scripts/cellcounter.py
picellcounter-1.0.4.dist-info/METADATA
picellcounter-1.0.4.dist-info/RECORD
picellcounter-1.0.4.dist-info/WHEEL
picellcounter-1.0.4.dist-info/top_level.txt
